setup.py
pyiacsun/__init__.py
pyiacsun.egg-info/PKG-INFO
pyiacsun.egg-info/SOURCES.txt
pyiacsun.egg-info/dependency_links.txt
pyiacsun.egg-info/not-zip-safe
pyiacsun.egg-info/pbr.json
pyiacsun.egg-info/requires.txt
pyiacsun.egg-info/top_level.txt
pyiacsun/atlas/__init__.py
pyiacsun/atlas/ftsread.py
pyiacsun/hazel/__init__.py
pyiacsun/hazel/genNetCDF.py
pyiacsun/hazel/i0Allen.py
pyiacsun/hazel/visHazel.py
pyiacsun/linalg/__init__.py
pyiacsun/linalg/cholInvert.py
pyiacsun/linalg/fsvd.py
pyiacsun/linalg/optimalSVHT.py
pyiacsun/linalg/rpcaRow.py
pyiacsun/machinelearn/__init__.py
pyiacsun/machinelearn/gpAndres.py
pyiacsun/machinelearn/rvm.py
pyiacsun/plot/__init__.py
pyiacsun/plot/tvframe.py
pyiacsun/radtran/LTEfull.py
pyiacsun/radtran/LTEnodes.py
pyiacsun/radtran/__init__.py
pyiacsun/radtran/voigt.py
pyiacsun/radtran/sourceHazel/SEE.f90
pyiacsun/radtran/sourceHazel/allen.f90
pyiacsun/radtran/sourceHazel/hazel.f90
pyiacsun/radtran/sourceHazel/io.f90
pyiacsun/radtran/sourceHazel/maths.f90
pyiacsun/radtran/sourceHazel/pyhazel.pyx
pyiacsun/radtran/sourceHazel/rt_coef.f90
pyiacsun/radtran/sourceHazel/singleton.f90
pyiacsun/radtran/sourceHazel/svd.f90
pyiacsun/radtran/sourceHazel/synth.f90
pyiacsun/radtran/sourceHazel/vars.f90
pyiacsun/radtran/sourceLTE/background.f90
pyiacsun/radtran/sourceLTE/hydros.f90
pyiacsun/radtran/sourceLTE/lte.f90
pyiacsun/radtran/sourceLTE/maths.f90
pyiacsun/radtran/sourceLTE/partition.f90
pyiacsun/radtran/sourceLTE/pylte.pyx
pyiacsun/radtran/sourceLTE/synth.f90
pyiacsun/radtran/sourceLTE/vars.f90
pyiacsun/radtran/sourceMilne/atomic.f90
pyiacsun/radtran/sourceMilne/maths.f90
pyiacsun/radtran/sourceMilne/milne.f90
pyiacsun/radtran/sourceMilne/pymilne.pyx
pyiacsun/radtran/sourceMilne/vars.f90
pyiacsun/sparse/__init__.py
pyiacsun/sparse/alps.py
pyiacsun/sparse/fasta.py
pyiacsun/sparse/iht.py
pyiacsun/sparse/iswt.py
pyiacsun/sparse/iuwt.py
pyiacsun/sparse/wavelet.py
pyiacsun/sparse/zeroSR1.py
pyiacsun/sparse/proxes/__init__.py
pyiacsun/sparse/proxes/prox_l0.py
pyiacsun/sparse/proxes/prox_l1.py
pyiacsun/sparse/proxes/prox_l1General.py
pyiacsun/sparse/proxes/prox_l2General.py
pyiacsun/sparse/proxes/prox_xlim.py
pyiacsun/util/__init__.py
pyiacsun/util/blink.py
